blast2xl/__init__.py
blast2xl/blast2xl.py
blast2xl/cli.py
blast2xl/io.py
blast2xl/log.py
blast2xl/util.py
blast2xl-0.1.0.dist-info/AUTHORS.rst
blast2xl-0.1.0.dist-info/LICENSE
blast2xl-0.1.0.dist-info/METADATA
blast2xl-0.1.0.dist-info/WHEEL
blast2xl-0.1.0.dist-info/entry_points.txt
blast2xl-0.1.0.dist-info/top_level.txt
blast2xl-0.1.0.dist-info/RECORD
