Metadata-Version: 2.1
Name: blast2xl
Version: 0.1.0
Summary: BLAST output to XLSX spreadsheet
Home-page: https://github.com/peterk87/blast2xl
Author: Peter Kruczkiewicz
Author-email: peter.kruczkiewicz@canada.ca
License: MIT license
Keywords: blast2xl
Platform: UNKNOWN
Classifier: Development Status :: 2 - Pre-Alpha
Classifier: Intended Audience :: Developers
Classifier: License :: OSI Approved :: MIT License
Classifier: Natural Language :: English
Classifier: Programming Language :: Python :: 3
Classifier: Programming Language :: Python :: 3.6
Classifier: Programming Language :: Python :: 3.7
Classifier: Programming Language :: Python :: 3.8
Requires-Python: >=3.6
Requires-Dist: Click (>=7.0)
Requires-Dist: pandas (>=0.25.0)
Requires-Dist: biopython (>=1.73)
Requires-Dist: xlsxwriter
